seq2annotation/__init__.py
seq2annotation/input.py
seq2annotation/input_paddle.py
seq2annotation/model.py
seq2annotation/model_paddle.py
seq2annotation/reportor.py
seq2annotation/unrandom.py
seq2annotation/utils.py
seq2annotation/algorithms/BiLSTM_CRF_model.py
seq2annotation/algorithms/IDCNN_CRF_model.py
seq2annotation/algorithms/Stacked_BiLSTM_CRF_model.py
seq2annotation/algorithms/__init__.py
seq2annotation/algorithms/model.py
seq2annotation/data/unicode_char_list.txt
seq2annotation/data_input/__init__.py
seq2annotation/health_check_transponder/__init__.py
seq2annotation/helper/__init__.py
seq2annotation/helper/create_datadir.py
seq2annotation/helper/end2end_inference.py
seq2annotation/helper/end2end_metrics.py
seq2annotation/helper/end2end_train.py
seq2annotation/helper/generate_constraint.py
seq2annotation/helper/generate_constraint_to_file.py
seq2annotation/metrics/__init__.py
seq2annotation/metrics/correct_rate.py
seq2annotation/metrics/tf_metrics.py
seq2annotation/preprocess_hooks/__init__.py
seq2annotation/preprocess_hooks/corpus_augment.py
seq2annotation/preprocess_hooks/corpus_drop.py
seq2annotation/preprocess_hooks/hook_base.py
seq2annotation/server/__init__.py
seq2annotation/server/http.py
seq2annotation/server/http_paddle.py
seq2annotation/server/legacy_http.py
seq2annotation/server/lookup_http.py
seq2annotation/server/ngram_http.py
seq2annotation/server/paddle_inference.py
seq2annotation/server/tensorflow_inference.py
seq2annotation/server/tensorflow_keras_h5_inference.py
seq2annotation/server/tensorflow_keras_savedmodel_inference.py
seq2annotation/server/NLP_server_frontend/.git
seq2annotation/server/NLP_server_frontend/NER.html
seq2annotation/server/NLP_server_frontend/NER.js
seq2annotation/server/NLP_server_frontend/README.md
seq2annotation/server/NLP_server_frontend/index.html
seq2annotation/server/NLP_server_frontend/paddlepaddle_tokenizer.html
seq2annotation/server/NLP_server_frontend/paddlepaddle_tokenizer.js
seq2annotation-0.14.1.dist-info/LICENSE
seq2annotation-0.14.1.dist-info/METADATA
seq2annotation-0.14.1.dist-info/WHEEL
seq2annotation-0.14.1.dist-info/top_level.txt
seq2annotation-0.14.1.dist-info/RECORD
